enexlib/__init__.py
enexlib/enexlib.py
enexlib-0.1.3.dist-info/METADATA
enexlib-0.1.3.dist-info/WHEEL
enexlib-0.1.3.dist-info/top_level.txt
enexlib-0.1.3.dist-info/RECORD
