Metadata-Version: 2.1
Name: enexlib
Version: 0.1.3
Summary: Convert Evernote backup files (.enex) to plaintext.
Project-URL: Source, https://github.com/whitgroves/enexlib
Keywords: evernote,enex
Requires-Python: >=3.9
Requires-Dist: beautifulsoup4 >=4.12.2
Requires-Dist: lxml >=4.9.3
Requires-Dist: soupsieve >=2.5
